actymath/__init__.py
actymath/calc.py
actymath/columns/__init__.py
actymath/columns/base.py
actymath/columns/commutation.py
actymath/columns/interest_rates.py
actymath/columns/mortality.py
actymath/columns/term.py
actymath/columns/timeline.py
actymath/columns/whole_of_life.py
actymath/exceptions.py
actymath/indexers.py
actymath/table_data/a1967-70.csv
actymath/table_data/a1967-70_exam.csv
actymath/table_data/amc00.csv
actymath/table_data/test.csv
actymath/table_data/test_lx.csv
actymath/tables.py
actymath-0.1.4.dist-info/LICENSE
actymath-0.1.4.dist-info/METADATA
actymath-0.1.4.dist-info/WHEEL
actymath-0.1.4.dist-info/RECORD
