Metadata-Version: 2.3
Name: actymath
Version: 0.1.4
Summary: Actuarial Math and commutation functions for life insurance product - with a Pandas backend
License: MIT
Keywords: actuarial,pandas,insurance
Author: Matt Gosden
Author-email: mdgosden@gmail.com
Requires-Python: >=3.8,<4.0
Classifier: License :: OSI Approved :: MIT License
Classifier: Programming Language :: Python :: 3
Classifier: Programming Language :: Python :: 3.8
Classifier: Programming Language :: Python :: 3.9
Classifier: Programming Language :: Python :: 3.10
Classifier: Programming Language :: Python :: 3.11
Classifier: Programming Language :: Python :: 3.12
Classifier: Programming Language :: Python :: 3.13
Requires-Dist: pandas (>=2.0.0,<3.0.0)
Requires-Dist: parse (>=1.19.0,<2.0.0)
Project-URL: Homepage, https://github.com/ttamg/actymath
Project-URL: Repository, https://github.com/ttamg/actymath
